pyOBabel-0.1.1.dist-info/WHEEL
pyOBabel-0.1.1.dist-info/top_level.txt
pyOBabel-0.1.1.dist-info/METADATA
pyOBabel-0.1.1.dist-info/RECORD
pyOBabel/__init__.py
pyOBabel/pyOBabel.cpython-34m.so
pyOBabel/.libs/libz-a147dcb0.so.1.2.3
