Metadata-Version: 1.1
Name: pyOBabel
Version: 0.1.1
Summary: A python binding to openbabel chemical toolbox (http://openbabel.org)
Home-page: https://github.com/rjdkmr/pyOBabel
Author: Rajendra Kumar
Author-email: rjdkmr@gmail.com
License: GNU General Public License v3 (GPLv3)
Keywords: Molecular Modeling,Chemoinformatics,Computational Chemistry,Computational Drug Design
Platform: UNKNOWN
Classifier: Environment :: Console
Classifier: Intended Audience :: Developers
Classifier: Intended Audience :: End Users/Desktop
Classifier: Intended Audience :: Science/Research
Classifier: License :: OSI Approved :: GNU General Public License v3 (GPLv3)
Classifier: Natural Language :: English
Classifier: Operating System :: MacOS
Classifier: Operating System :: POSIX :: Linux
Classifier: Topic :: Scientific/Engineering :: Bio-Informatics
